odoo9_addon_attachment_base_synchronize-9.0.1.0.0.99.dev37-py3.8-nspkg.pth
odoo_addons/attachment_base_synchronize/README.rst
odoo_addons/attachment_base_synchronize/__init__.py
odoo_addons/attachment_base_synchronize/__openerp__.py
odoo_addons/attachment_base_synchronize/data/cron.xml
odoo_addons/attachment_base_synchronize/demo/attachment_metadata_demo.xml
odoo_addons/attachment_base_synchronize/i18n/am.po
odoo_addons/attachment_base_synchronize/i18n/ar.po
odoo_addons/attachment_base_synchronize/i18n/attachment_base_synchronize.pot
odoo_addons/attachment_base_synchronize/i18n/bg.po
odoo_addons/attachment_base_synchronize/i18n/bs.po
odoo_addons/attachment_base_synchronize/i18n/ca.po
odoo_addons/attachment_base_synchronize/i18n/ca_ES.po
odoo_addons/attachment_base_synchronize/i18n/cs.po
odoo_addons/attachment_base_synchronize/i18n/da.po
odoo_addons/attachment_base_synchronize/i18n/de.po
odoo_addons/attachment_base_synchronize/i18n/el_GR.po
odoo_addons/attachment_base_synchronize/i18n/en.po
odoo_addons/attachment_base_synchronize/i18n/en_GB.po
odoo_addons/attachment_base_synchronize/i18n/es.po
odoo_addons/attachment_base_synchronize/i18n/es_AR.po
odoo_addons/attachment_base_synchronize/i18n/es_CL.po
odoo_addons/attachment_base_synchronize/i18n/es_CO.po
odoo_addons/attachment_base_synchronize/i18n/es_CR.po
odoo_addons/attachment_base_synchronize/i18n/es_DO.po
odoo_addons/attachment_base_synchronize/i18n/es_EC.po
odoo_addons/attachment_base_synchronize/i18n/es_ES.po
odoo_addons/attachment_base_synchronize/i18n/es_MX.po
odoo_addons/attachment_base_synchronize/i18n/es_PE.po
odoo_addons/attachment_base_synchronize/i18n/es_PY.po
odoo_addons/attachment_base_synchronize/i18n/es_VE.po
odoo_addons/attachment_base_synchronize/i18n/et.po
odoo_addons/attachment_base_synchronize/i18n/eu.po
odoo_addons/attachment_base_synchronize/i18n/fa.po
odoo_addons/attachment_base_synchronize/i18n/fi.po
odoo_addons/attachment_base_synchronize/i18n/fr.po
odoo9_addon_attachment_base_synchronize-9.0.1.0.0.99.dev37.dist-info/METADATA
odoo9_addon_attachment_base_synchronize-9.0.1.0.0.99.dev37.dist-info/WHEEL
odoo9_addon_attachment_base_synchronize-9.0.1.0.0.99.dev37.dist-info/namespace_packages.txt
odoo9_addon_attachment_base_synchronize-9.0.1.0.0.99.dev37.dist-info/top_level.txt
odoo9_addon_attachment_base_synchronize-9.0.1.0.0.99.dev37.dist-info/RECORD
